{
  "autonomousSteps" : [ {
    "type" : "script",
    "script" : "@t 0.7\nClimber.deployClimb\nDrive.setRotation 0",
    "closed" : false,
    "valid" : true,
    "sendableScript" : {
      "delayType" : "TIME",
      "delay" : 0.7,
      "commands" : [ {
        "methodName" : "frc.subsystem.Climber.deployClimb",
        "args" : [ ],
        "argTypes" : [ ],
        "reflection" : true
      }, {
        "methodName" : "frc.subsystem.Drive.setRotation",
        "args" : [ "0" ],
        "argTypes" : [ "double" ],
        "reflection" : true
      } ]
    }
  }, {
    "type" : "trajectory",
    "states" : [ {
      "time" : 0.0,
      "velocity" : 0.0,
      "acceleration" : 4.000000000000001,
      "pose" : {
        "translation" : {
          "x" : 16.01304054260254,
          "y" : -2.1678781509399414
        },
        "rotation" : {
          "radians" : -3.054950883982713
        }
      },
      "curvature" : 0.0
    }, {
      "time" : 0.20901420175114013,
      "velocity" : 0.8360568070045608,
      "acceleration" : 4.000000000000001,
      "pose" : {
        "translation" : {
          "x" : 15.925995533490038,
          "y" : -2.175451794936791
        },
        "rotation" : {
          "radians" : -3.0545135321150867
        }
      },
      "curvature" : 0.009736334541399905
    }, {
      "time" : 0.29401893731352774,
      "velocity" : 1.1760757492541112,
      "acceleration" : 4.000000000000002,
      "pose" : {
        "translation" : {
          "x" : 15.840803209312071,
          "y" : -2.1829355348686477
        },
        "rotation" : {
          "radians" : -3.0533069976686606
        }
      },
      "curvature" : 0.01846664978473079
    }, {
      "time" : 0.3571020004796104,
      "velocity" : 1.4284080019184417,
      "acceleration" : 3.9999999999999973,
      "pose" : {
        "translation" : {
          "x" : 15.758980125617938,
          "y" : -2.190250448558132
        },
        "rotation" : {
          "radians" : -3.0514331039009877
        }
      },
      "curvature" : 0.027319857600219405
    }, {
      "time" : 0.40782880135029265,
      "velocity" : 1.6313152054011706,
      "acceleration" : 3.999999999999997,
      "pose" : {
        "translation" : {
          "x" : 15.681698644475546,
          "y" : -2.197329033035203
        },
        "rotation" : {
          "radians" : -3.048946215811507
        }
      },
      "curvature" : 0.03708352830974944
    }, {
      "time" : 0.4499195321482518,
      "velocity" : 1.799678128593007,
      "acceleration" : 4.0,
      "pose" : {
        "translation" : {
          "x" : 15.609811676904144,
          "y" : -2.204114587400099
        },
        "rotation" : {
          "radians" : -3.04587725145468
        }
      },
      "curvature" : 0.04836619660623272
    }, {
      "time" : 0.48533687653778396,
      "velocity" : 1.9413475061511356,
      "acceleration" : 3.9999999999999982,
      "pose" : {
        "translation" : {
          "x" : 15.543877425307073,
          "y" : -2.2105605956862746
        },
        "rotation" : {
          "radians" : -3.0422533500904243
        }
      },
      "curvature" : 0.06158200895765614
    }, {
      "time" : 0.5407464786883603,
      "velocity" : 2.162985914753441,
      "acceleration" : -2.885840674308159,
      "pose" : {
        "translation" : {
          "x" : 15.430774791166186,
          "y" : -2.2222951319999993
        },
        "rotation" : {
          "radians" : -3.0335745442965862
        }
      },
      "curvature" : 0.0928483747405819
    }, {
      "time" : 0.583304173291436,
      "velocity" : 2.0401711886631,
      "acceleration" : -4.00000000000001,
      "pose" : {
        "translation" : {
          "x" : 15.341902401405605,
          "y" : -2.2323407617000157
        },
        "rotation" : {
          "radians" : -3.0241936060730907
        }
      },
      "curvature" : 0.11146880391177004
    }, {
      "time" : 0.6182029575454727,
      "velocity" : 1.9005760516469532,
      "acceleration" : -4.0,
      "pose" : {
        "translation" : {
          "x" : 15.273640093219,
          "y" : -2.2406290666694986
        },
        "rotation" : {
          "radians" : -3.01822293918896
        }
      },
      "curvature" : 0.02831128879606893
    }, {
      "time" : 0.6745521854247815,
      "velocity" : 1.6751791401297182,
      "acceleration" : 4.0,
      "pose" : {
        "translation" : {
          "x" : 15.173556506633759,
          "y" : -2.2521588504314423
        },
        "rotation" : {
          "radians" : -3.0493995532133433
        }
      },
      "curvature" : -0.7241044072658259
    }, {
      "time" : 0.7329825863797574,
      "velocity" : 1.908900743949622,
      "acceleration" : 4.000000000000003,
      "pose" : {
        "translation" : {
          "x" : 15.069013083993923,
          "y" : -2.2580559428752167
        },
        "rotation" : {
          "radians" : -3.1129352348383637
        }
      },
      "curvature" : -0.3448797260468909
    }, {
      "time" : 0.7701533524368848,
      "velocity" : 2.0575838081781312,
      "acceleration" : 3.9844394720069047,
      "pose" : {
        "translation" : {
          "x" : 14.995308015359115,
          "y" : -2.2594701410057496
        },
        "rotation" : {
          "radians" : -3.1293428440213913
        }
      },
      "curvature" : -0.13519814614850387
    }, {
      "time" : 0.8149848185251733,
      "velocity" : 2.2362120712482474,
      "acceleration" : -4.0,
      "pose" : {
        "translation" : {
          "x" : 14.899062225595117,
          "y" : -2.2602033014409244
        },
        "rotation" : {
          "radians" : -3.1372226474037874
        }
      },
      "curvature" : -0.046367826981332266
    }, {
      "time" : 0.8725799676090057,
      "velocity" : 2.005831474912918,
      "acceleration" : -3.9999999999999907,
      "pose" : {
        "translation" : {
          "x" : 14.77690201651967,
          "y" : -2.260498286373604
        },
        "rotation" : {
          "radians" : -3.140491337841853
        }
      },
      "curvature" : -0.013860468539065472
    }, {
      "time" : 0.9093219870956158,
      "velocity" : 1.8588633969664778,
      "acceleration" : -4.000000000000003,
      "pose" : {
        "translation" : {
          "x" : 14.70590368709992,
          "y" : -2.260548457046653
        },
        "rotation" : {
          "radians" : -3.141197544835221
        }
      },
      "curvature" : -0.006781763662677531
    }, {
      "time" : 0.9529239069222338,
      "velocity" : 1.6844557176600057,
      "acceleration" : -4.0,
      "pose" : {
        "translation" : {
          "x" : 14.628655930573586,
          "y" : -2.260563433068455
        },
        "rotation" : {
          "radians" : -3.1415484329867986
        }
      },
      "curvature" : -0.002744819647192182
    }, {
      "time" : 1.0054014876896404,
      "velocity" : 1.474545394590379,
      "acceleration" : -3.9999999999999987,
      "pose" : {
        "translation" : {
          "x" : 14.545767562615026,
          "y" : -2.2605606221074908
        },
        "rotation" : {
          "radians" : 3.1415103938702558
        }
      },
      "curvature" : -5.723219544943866E-4
    }, {
      "time" : 1.0705872960565475,
      "velocity" : 1.2138021611227512,
      "acceleration" : -4.000000000000002,
      "pose" : {
        "translation" : {
          "x" : 14.458146508668506,
          "y" : -2.2605528054759816
        },
        "rotation" : {
          "radians" : 3.1415107491933503
        }
      },
      "curvature" : 4.1220924274731343E-4
    }, {
      "time" : 1.158349985088619,
      "velocity" : 0.8627514049944651,
      "acceleration" : -3.9999999999999996,
      "pose" : {
        "translation" : {
          "x" : 14.367024546380947,
          "y" : -2.26054752099283
        },
        "rotation" : {
          "radians" : 3.1415608259916934
        }
      },
      "curvature" : 5.638219560301437E-4
    }, {
      "time" : 1.3740378363372352,
      "velocity" : 0.0,
      "acceleration" : -3.9999999999999996,
      "pose" : {
        "translation" : {
          "x" : 14.273982048034668,
          "y" : -2.2605464458465576
        },
        "rotation" : {
          "radians" : 3.141592653589793
        }
      },
      "curvature" : -0.0
    } ],
    "pointList" : [ {
      "x" : [ 16.01304054260254, -2.795994758605957, 0.0 ],
      "y" : [ -2.1678781509399414, -0.2428579330444336, 0.0 ]
    }, {
      "x" : [ 14.273982048034668, -2.988284111022949, 0.0 ],
      "y" : [ -2.2605464458465576, 0.0, 0.0 ]
    } ],
    "rotations" : [ {
      "time" : 0.0,
      "rotation" : {
        "radians" : 0.0
      }
    }, {
      "time" : 1.289999971166253,
      "rotation" : {
        "radians" : 0.0
      }
    } ],
    "reversed" : false,
    "color" : 4.470581,
    "closed" : false,
    "velocityStart" : 0.0,
    "velocityEnd" : 0.0,
    "constraints" : [ ]
  } ]
}